roboml/__init__.py
roboml/interfaces.py
roboml/main.py
roboml/utils.py
roboml/models/__init__.py
roboml/models/_base.py
roboml/models/llm.py
roboml/models/mllm.py
roboml/models/planning.py
roboml/models/speech_to_text.py
roboml/models/text_to_speech.py
roboml/models/vision.py
roboml/ray/__init__.py
roboml/ray/app_factory.py
roboml/ray/node.py
roboml/resp_server/node.py
roboml/resp_server/server.py
roboml/resp_server/stream.py
roboml/tools/__init__.py
roboml/tools/download.py
roboml-0.3.1.dist-info/licenses/LICENSE
roboml-0.3.1.dist-info/METADATA
roboml-0.3.1.dist-info/WHEEL
roboml-0.3.1.dist-info/entry_points.txt
roboml-0.3.1.dist-info/top_level.txt
roboml-0.3.1.dist-info/RECORD
