Metadata-Version: 2.4
Name: roboml
Version: 0.3.1
Summary: Machine learning models optimized for robotics experimentation and deployment
Author-email: Automatika Robotics <contact@automatikarobotics.com>
License: MIT
Project-URL: Homepage, https://github.com/automatika-robotics/roboml
Keywords: robots,robotics,machine learning,multimodal,deep learning
Classifier: License :: OSI Approved :: MIT License
Classifier: Programming Language :: Python :: 3
Classifier: Programming Language :: Python :: 3.10
Classifier: Programming Language :: Python :: 3.11
Classifier: Programming Language :: Python :: 3.12
Classifier: Programming Language :: Python :: 3.13
Requires-Python: >=3.10
License-File: LICENSE
Requires-Dist: torch<=2.4
Requires-Dist: accelerate
Requires-Dist: transformers
Requires-Dist: bitsandbytes
Requires-Dist: pillow
Requires-Dist: msgpack
Requires-Dist: msgpack_numpy
Requires-Dist: hiredis
Requires-Dist: ray[serve]
Requires-Dist: datasets
Requires-Dist: scipy
Requires-Dist: ninja
Requires-Dist: packaging
Requires-Dist: ctranslate2<=4.4
Requires-Dist: faster-whisper
Provides-Extra: dev
Requires-Dist: httpx; extra == "dev"
Requires-Dist: pip-tools; extra == "dev"
Requires-Dist: pytest; extra == "dev"
Requires-Dist: pre-commit; extra == "dev"
Requires-Dist: redis; extra == "dev"
Requires-Dist: lark; extra == "dev"
Provides-Extra: vision
Requires-Dist: mmengine; extra == "vision"
Requires-Dist: platformdirs; extra == "vision"
Requires-Dist: norfair; extra == "vision"
Requires-Dist: mmdeploy==1.3.1; platform_machine == "x86_64" and extra == "vision"
Requires-Dist: mmdeploy-runtime-gpu==1.3.1; platform_machine == "x86_64" and extra == "vision"
Requires-Dist: pycuda; extra == "vision"
Requires-Dist: opencv-python-headless; extra == "vision"
Dynamic: license-file
